flashgeotext/__init__.py
flashgeotext/config.py
flashgeotext/geotext.py
flashgeotext/lookup.py
flashgeotext/resources/cities.json
flashgeotext/resources/countries.json
flashgeotext/resources/scripts.json
flashgeotext/settings.py
flashgeotext-0.5.5.dist-info/LICENSE
flashgeotext-0.5.5.dist-info/METADATA
flashgeotext-0.5.5.dist-info/WHEEL
flashgeotext-0.5.5.dist-info/RECORD
