Metadata-Version: 2.3
Name: flashgeotext
Version: 0.5.5
Summary: Extract and count countries and cities (+their synonyms) from text
License: MIT
Keywords: geonames,nlp,text extraction
Author: Benjamin Ramser
Author-email: ahoi@iwpnd.pw
Requires-Python: >=3.10.0,<4.0.0
Classifier: Intended Audience :: Developers
Classifier: License :: OSI Approved :: MIT License
Classifier: Operating System :: OS Independent
Classifier: Programming Language :: Python
Classifier: Programming Language :: Python :: 3
Classifier: Programming Language :: Python :: 3.10
Classifier: Programming Language :: Python :: 3.11
Classifier: Programming Language :: Python :: 3.12
Classifier: Programming Language :: Python :: 3.13
Classifier: Programming Language :: Python :: 3 :: Only
Classifier: Topic :: Software Development :: Libraries
Classifier: Topic :: Software Development :: Libraries :: Python Modules
Classifier: Typing :: Typed
Requires-Dist: flashtext (>=2.7,<3.0)
Requires-Dist: loguru (>=0.5.0)
Requires-Dist: pydantic (>=2.7.0)
Project-URL: Homepage, https://flashgeotext.iwpnd.pw
Project-URL: Repository, https://github.com/iwpnd/flashgeotext
